herbal/__init__.py
herbal/__main__.py
herbal/block_cipher.py
herbal/py.typed
herbal/tea.py
herbal/types_.py
herbal/xtea.py
herbal-0.1.3.dist-info/LICENSE
herbal-0.1.3.dist-info/METADATA
herbal-0.1.3.dist-info/WHEEL
herbal-0.1.3.dist-info/RECORD
