Metadata-Version: 2.1
Name: herbal
Version: 0.1.3
Summary: Python package for the Tiny Encryption Algorithm (TEA).
Home-page: https://gitlab.com/lunardev/herbal
License: MIT
Keywords: python,python3,block cipher,cryptography,tiny encryption algorithm,tea
Author: T. Rodriguez
Requires-Python: >=3.9,<4.0
Classifier: Development Status :: 1 - Planning
Classifier: Environment :: Console
Classifier: Intended Audience :: Developers
Classifier: Intended Audience :: End Users/Desktop
Classifier: License :: OSI Approved :: MIT License
Classifier: Natural Language :: English
Classifier: Operating System :: MacOS :: MacOS X
Classifier: Operating System :: Microsoft :: Windows :: Windows 10
Classifier: Operating System :: Microsoft :: Windows :: Windows 11
Classifier: Operating System :: POSIX :: Linux
Classifier: Programming Language :: Python :: 3
Classifier: Programming Language :: Python :: 3.9
Classifier: Programming Language :: Python :: 3.10
Classifier: Programming Language :: Python :: 3.11
Classifier: Programming Language :: Python :: 3.12
Classifier: Programming Language :: Python :: Implementation :: CPython
Classifier: Topic :: Security :: Cryptography
Classifier: Topic :: Utilities
Classifier: Typing :: Typed
Project-URL: Repository, https://gitlab.com/lunardev/herbal
